.DS_Store
tabledai/__init__.py
tabledai/create.py
tabledai/postgres/__init__.py
tabledai/postgres/database_management.py
tabledai/postgres/llm_integration.py
tabledai/postgres/query_handling.py
tabledai/postgres/utils.py
tabledai-0.0.37.dist-info/LICENSE
tabledai-0.0.37.dist-info/METADATA
tabledai-0.0.37.dist-info/WHEEL
tabledai-0.0.37.dist-info/top_level.txt
tabledai-0.0.37.dist-info/RECORD
