Metadata-Version: 2.1
Name: tabledai
Version: 0.0.37
Author: Vince Berry
Author-email: vincent.berry11@gmail.com
Keywords: python,ai,ml,nlp,sql,postgres
Classifier: Development Status :: 1 - Planning
Classifier: Intended Audience :: Developers
Classifier: Programming Language :: Python :: 3
Classifier: Operating System :: Unix
Classifier: Operating System :: MacOS :: MacOS X
Classifier: Operating System :: Microsoft :: Windows
License-File: LICENSE
Requires-Dist: pandas
Requires-Dist: sqlalchemy
Requires-Dist: psycopg2-binary
Requires-Dist: python-dotenv
Requires-Dist: openai
Requires-Dist: chardet
